megatron_tokenizer_lite/__init__.py
megatron_tokenizer_lite/indexed_dataset.py
megatron_tokenizer_lite-0.0.2.dist-info/METADATA
megatron_tokenizer_lite-0.0.2.dist-info/WHEEL
megatron_tokenizer_lite-0.0.2.dist-info/licenses/LICENSE
megatron_tokenizer_lite-0.0.2.dist-info/RECORD
